{
  "stats": {
    "suites": 3,
    "tests": 3,
    "passes": 3,
    "pending": 0,
    "failures": 0,
    "start": "2019-08-04T16:16:13.974Z",
    "end": "2019-08-04T16:16:13.984Z",
    "duration": 10
  },
  "tests": [
    {
      "title": "must have version v8.16.0",
      "fullTitle": "node must have version v8.16.0",
      "duration": 1,
      "currentRetry": 0,
      "err": {}
    },
    {
      "title": "must be darwin,linux",
      "fullTitle": "platform must be darwin,linux",
      "duration": 1,
      "currentRetry": 0,
      "err": {}
    },
    {
      "title": "must be undefined",
      "fullTitle": "env var NODE_ENV must be undefined",
      "duration": 0,
      "currentRetry": 0,
      "err": {}
    }
  ],
  "pending": [],
  "failures": [],
  "passes": [
    {
      "title": "must have version v8.16.0",
      "fullTitle": "node must have version v8.16.0",
      "duration": 1,
      "currentRetry": 0,
      "err": {}
    },
    {
      "title": "must be darwin,linux",
      "fullTitle": "platform must be darwin,linux",
      "duration": 1,
      "currentRetry": 0,
      "err": {}
    },
    {
      "title": "must be undefined",
      "fullTitle": "env var NODE_ENV must be undefined",
      "duration": 0,
      "currentRetry": 0,
      "err": {}
    }
  ]
}